LICENSE
MANIFEST.in
README.md
requirements.txt
setup.py
oxasl_multite/__init__.py
oxasl_multite/_version.py
oxasl_multite/api.py
oxasl_multite.egg-info/PKG-INFO
oxasl_multite.egg-info/SOURCES.txt
oxasl_multite.egg-info/dependency_links.txt
oxasl_multite.egg-info/requires.txt
oxasl_multite.egg-info/top_level.txt